{
	"bootFeatures": "FTR_DEMO_SUB",

	"datasource": [
	
		{"type": "Asm_Data", "level": "demo", "task": "Subtract single digits no Borrow", "dataset": [7,2,5], "operation": "-", "image": "star"},

		{"type": "Asm_Data", "level": "demo", "task": "Subtract single digits no Borrow", "dataset": [6,2,4], "operation": "-", "image": "star"},

		{"type": "Asm_Data", "level": "demo", "task": "Subtract single digits no Borrow", "dataset": [8,5,3], "operation": "-", "image": "star"},

		{"type": "Asm_Data", "level": "demo", "task": "Subtract single digits no Borrow", "dataset": [5,1,4], "operation": "-", "image": "star"},

		{"type": "Asm_Data", "level": "demo", "task": "Subtract single digits no Borrow", "dataset": [6,2,4], "operation": "-", "image": "star"},

		{"type": "Asm_Data", "level": "demo", "task": "Subtract single digits no Borrow", "dataset": [7,3,4], "operation": "-", "image": "star"},

		{"type": "Asm_Data", "level": "demo", "task": "Subtract single digits no Borrow", "dataset": [4,0,4], "operation": "-", "image": "star"},

		{"type": "Asm_Data", "level": "demo", "task": "Subtract single digits no Borrow", "dataset": [7,6,1], "operation": "-", "image": "star"},

		{"type": "Asm_Data", "level": "demo", "task": "Subtract single digits no Borrow", "dataset": [8,4,4], "operation": "-", "image": "star"}]

}